{
  "games": [
    {
      "id": 0,
      "name": "Direct Assurance Technician",
      "semester": "1",
      "year": 2000,
      "cover_image": "http://lorempixel.com/640/480",
      "description": "Veniam molestiae aliquam. Dicta reprehenderit ut. Consequatur repellendus unde culpa deserunt doloremque hic sit.",
      "platform_packages": "linux",
      "awards": {
        "song": false,
        "implementation": false,
        "design": false,
        "best_game": false
      },
      "game_images": ["images"],
      "images_gallery": ["images"],
      "sound_gallery": ["songs"]
    },
    {
      "id": 1,
      "name": "Future Identity Facilitator",
      "semester": "1",
      "year": 2000,
      "cover_image": "http://lorempixel.com/640/480",
      "description": "Molestiae asperiores magni temporibus explicabo officiis quasi quis itaque. Eius qui repellendus consequatur. Quae repellat rerum ipsum non voluptate aliquid.",
      "platform_packages": "linux",
      "awards": {
        "song": false,
        "implementation": false,
        "design": false,
        "best_game": false
      },
      "game_images": ["images"],
      "images_gallery": ["images"],
      "sound_gallery": ["songs"]
    },
    {
      "id": 2,
      "name": "Customer Paradigm Executive",
      "semester": "1",
      "year": 2000,
      "cover_image": "http://lorempixel.com/640/480",
      "description": "Iure molestiae nisi quas perferendis qui omnis rerum nisi cumque. Nostrum numquam reiciendis. Dolor temporibus enim. Quia aut assumenda expedita labore. Totam occaecati repellendus doloremque qui.",
      "platform_packages": "linux",
      "awards": {
        "song": false,
        "implementation": false,
        "design": false,
        "best_game": false
      },
      "game_images": ["images"],
      "images_gallery": ["images"],
      "sound_gallery": ["songs"]
    },
    {
      "id": 3,
      "name": "Lead Communications Agent",
      "semester": "1",
      "year": 2000,
      "cover_image": "http://lorempixel.com/640/480",
      "description": "Harum totam quis ea facilis tenetur. Consequatur autem totam. Magni possimus blanditiis adipisci. Eum voluptatibus ducimus aut et necessitatibus reiciendis minus et voluptatem. Commodi eos dolorem est totam unde laborum eos maiores aperiam. Perferendis veniam ea accusantium.",
      "platform_packages": "linux",
      "awards": {
        "song": false,
        "implementation": false,
        "design": false,
        "best_game": false
      },
      "game_images": ["images"],
      "images_gallery": ["images"],
      "sound_gallery": ["songs"]
    },
    {
      "id": 4,
      "name": "International Data Consultant",
      "semester": "1",
      "year": 2000,
      "cover_image": "http://lorempixel.com/640/480",
      "description": "Totam a facilis. Optio velit molestias nobis quae dolore porro. Omnis cum deserunt laboriosam sunt similique blanditiis consectetur et molestiae. Qui voluptatem ut voluptas impedit est praesentium doloribus ipsam quod. Dolor minus autem voluptas aut saepe. Aut sequi expedita facilis est assumenda magni a dolore reprehenderit.",
      "platform_packages": "linux",
      "awards": {
        "song": false,
        "implementation": false,
        "design": false,
        "best_game": false
      },
      "game_images": ["images"],
      "images_gallery": ["images"],
      "sound_gallery": ["songs"]
    },
    {
      "id": 5,
      "name": "Chief Operations Executive",
      "semester": "1",
      "year": 2000,
      "cover_image": "http://lorempixel.com/640/480",
      "description": "Est perferendis voluptate ut aut eum ipsam quia ut incidunt. Incidunt harum ut porro quia ea nobis sed. Doloremque qui dolores minus occaecati dolore aliquam aperiam.",
      "platform_packages": "linux",
      "awards": {
        "song": false,
        "implementation": false,
        "design": false,
        "best_game": false
      },
      "game_images": ["images"],
      "images_gallery": ["images"],
      "sound_gallery": ["songs"]
    },
    {
      "id": 6,
      "name": "Corporate Assurance Agent",
      "semester": "1",
      "year": 2000,
      "cover_image": "http://lorempixel.com/640/480",
      "description": "Velit delectus soluta quia placeat ullam facilis aliquid praesentium hic. Modi odio sunt quos. Commodi officiis consequatur corrupti quod exercitationem modi qui. Fugit nihil distinctio possimus molestiae omnis deserunt magnam est.",
      "platform_packages": "linux",
      "awards": {
        "song": false,
        "implementation": false,
        "design": false,
        "best_game": false
      },
      "game_images": ["images"],
      "images_gallery": ["images"],
      "sound_gallery": ["songs"]
    },
    {
      "id": 7,
      "name": "Product Branding Coordinator",
      "semester": "1",
      "year": 2000,
      "cover_image": "http://lorempixel.com/640/480",
      "description": "Incidunt laudantium eos eius ut eum impedit nihil est. Neque voluptas adipisci quia accusamus. Asperiores consequatur rerum aut.",
      "platform_packages": "linux",
      "awards": {
        "song": false,
        "implementation": false,
        "design": false,
        "best_game": false
      },
      "game_images": ["images"],
      "images_gallery": ["images"],
      "sound_gallery": ["songs"]
    },
    {
      "id": 8,
      "name": "Dynamic Interactions Strategist",
      "semester": "1",
      "year": 2000,
      "cover_image": "http://lorempixel.com/640/480",
      "description": "Molestias odit repellat nobis labore facere aut voluptatem ut ut. Maiores nihil alias aperiam adipisci. Tenetur qui doloribus repellat quia. Cupiditate odit rerum consequatur reiciendis. Cum eveniet repudiandae doloremque qui. Rerum et quae alias sed.",
      "platform_packages": "linux",
      "awards": {
        "song": false,
        "implementation": false,
        "design": false,
        "best_game": false
      },
      "game_images": ["images"],
      "images_gallery": ["images"],
      "sound_gallery": ["songs"]
    },
    {
      "id": 9,
      "name": "National Intranet Executive",
      "semester": "1",
      "year": 2000,
      "cover_image": "http://lorempixel.com/640/480",
      "description": "Rerum magni assumenda voluptatem. Harum aliquam blanditiis enim quidem eius. Assumenda dicta et. Consectetur rerum incidunt magnam quos quia id explicabo.",
      "platform_packages": "linux",
      "awards": {
        "song": false,
        "implementation": false,
        "design": false,
        "best_game": false
      },
      "game_images": ["images"],
      "images_gallery": ["images"],
      "sound_gallery": ["songs"]
    },
    {
      "id": 10,
      "name": "Corporate Usability Consultant",
      "semester": "1",
      "year": 2000,
      "cover_image": "http://lorempixel.com/640/480",
      "description": "Ratione quis alias illo officia incidunt et ea recusandae. Sed enim animi in. Quia possimus velit minima ut. Pariatur nemo saepe fugiat deleniti asperiores rerum molestiae. Tempore alias qui laboriosam sed ipsum est asperiores.",
      "platform_packages": "linux",
      "awards": {
        "song": false,
        "implementation": false,
        "design": false,
        "best_game": false
      },
      "game_images": ["images"],
      "images_gallery": ["images"],
      "sound_gallery": ["songs"]
    },
    {
      "id": 11,
      "name": "Direct Accounts Producer",
      "semester": "1",
      "year": 2000,
      "cover_image": "http://lorempixel.com/640/480",
      "description": "Eaque consectetur dolores quod hic autem odit explicabo. Nobis quas est et. Beatae esse nihil. Dolorem reprehenderit asperiores. Expedita debitis soluta cumque.",
      "platform_packages": "linux",
      "awards": {
        "song": false,
        "implementation": false,
        "design": false,
        "best_game": false
      },
      "game_images": ["images"],
      "images_gallery": ["images"],
      "sound_gallery": ["songs"]
    },
    {
      "id": 12,
      "name": "Lead Accountability Specialist",
      "semester": "1",
      "year": 2000,
      "cover_image": "http://lorempixel.com/640/480",
      "description": "Excepturi repudiandae vero magnam. Ea perferendis sunt libero enim. Possimus hic praesentium necessitatibus maiores commodi vitae dolorum. Cumque labore modi qui aut voluptate occaecati veritatis. Non dicta corrupti eos quia qui.",
      "platform_packages": "linux",
      "awards": {
        "song": false,
        "implementation": false,
        "design": false,
        "best_game": false
      },
      "game_images": ["images"],
      "images_gallery": ["images"],
      "sound_gallery": ["songs"]
    },
    {
      "id": 13,
      "name": "Chief Solutions Director",
      "semester": "1",
      "year": 2000,
      "cover_image": "http://lorempixel.com/640/480",
      "description": "Consequatur rerum omnis quos et qui illum quaerat consequatur. In ut deserunt optio. Voluptas in labore corporis quas nihil ipsa voluptas dicta. Commodi sunt non rerum impedit dicta.",
      "platform_packages": "linux",
      "awards": {
        "song": false,
        "implementation": false,
        "design": false,
        "best_game": false
      },
      "game_images": ["images"],
      "images_gallery": ["images"],
      "sound_gallery": ["songs"]
    },
    {
      "id": 14,
      "name": "Dynamic Tactics Consultant",
      "semester": "1",
      "year": 2000,
      "cover_image": "http://lorempixel.com/640/480",
      "description": "Commodi est reiciendis optio voluptate magnam eos. Nihil aut repudiandae libero numquam non tempora. Rem molestias veritatis ex aut maxime. Et ad et. Velit numquam aut rerum repudiandae vel sapiente ullam.",
      "platform_packages": "linux",
      "awards": {
        "song": false,
        "implementation": false,
        "design": false,
        "best_game": false
      },
      "game_images": ["images"],
      "images_gallery": ["images"],
      "sound_gallery": ["songs"]
    },
    {
      "id": 15,
      "name": "Central Metrics Analyst",
      "semester": "1",
      "year": 2000,
      "cover_image": "http://lorempixel.com/640/480",
      "description": "Iusto perspiciatis molestias itaque ex. Excepturi impedit sunt sed quisquam ad minus sunt id et. Modi est eos perferendis.",
      "platform_packages": "linux",
      "awards": {
        "song": false,
        "implementation": false,
        "design": false,
        "best_game": false
      },
      "game_images": ["images"],
      "images_gallery": ["images"],
      "sound_gallery": ["songs"]
    },
    {
      "id": 16,
      "name": "National Identity Architect",
      "semester": "1",
      "year": 2000,
      "cover_image": "http://lorempixel.com/640/480",
      "description": "Amet aut repudiandae quod. Vel unde nihil voluptates minima. Quibusdam qui quos officiis et animi dolore modi occaecati ab. Laboriosam qui culpa vitae. Commodi consequatur est rem molestias.",
      "platform_packages": "linux",
      "awards": {
        "song": false,
        "implementation": false,
        "design": false,
        "best_game": false
      },
      "game_images": ["images"],
      "images_gallery": ["images"],
      "sound_gallery": ["songs"]
    },
    {
      "id": 17,
      "name": "Product Communications Analyst",
      "semester": "1",
      "year": 2000,
      "cover_image": "http://lorempixel.com/640/480",
      "description": "Voluptatem velit sapiente rem. Aut sed et placeat sed beatae tenetur. Sit nisi explicabo ut maxime vero. Praesentium est ut et expedita earum nemo et. Eos voluptatem eos.",
      "platform_packages": "linux",
      "awards": {
        "song": false,
        "implementation": false,
        "design": false,
        "best_game": false
      },
      "game_images": ["images"],
      "images_gallery": ["images"],
      "sound_gallery": ["songs"]
    },
    {
      "id": 18,
      "name": "Investor Infrastructure Facilitator",
      "semester": "1",
      "year": 2000,
      "cover_image": "http://lorempixel.com/640/480",
      "description": "Nihil quia vero quis et nostrum accusantium laboriosam et. Et quo dolorem praesentium. Suscipit voluptatem perspiciatis et qui animi. Omnis iure rerum rem reiciendis. Distinctio excepturi sunt voluptatem.",
      "platform_packages": "linux",
      "awards": {
        "song": false,
        "implementation": false,
        "design": false,
        "best_game": false
      },
      "game_images": ["images"],
      "images_gallery": ["images"],
      "sound_gallery": ["songs"]
    },
    {
      "id": 19,
      "name": "Regional Mobility Director",
      "semester": "1",
      "year": 2000,
      "cover_image": "http://lorempixel.com/640/480",
      "description": "Dicta cum sed tempora. Consequatur odio iste soluta vel commodi consequatur harum. Quis provident aut dolorem. Qui quibusdam omnis eos expedita voluptas odit exercitationem.",
      "platform_packages": "linux",
      "awards": {
        "song": false,
        "implementation": false,
        "design": false,
        "best_game": false
      },
      "game_images": ["images"],
      "images_gallery": ["images"],
      "sound_gallery": ["songs"]
    },
    {
      "id": 20,
      "name": "International Program Strategist",
      "semester": "1",
      "year": 2000,
      "cover_image": "http://lorempixel.com/640/480",
      "description": "Magnam est dolor. Sit ut et modi libero repellat voluptatem a tempora quo. Iste facere itaque eos et consequatur. Voluptates totam officia qui dignissimos doloribus. Delectus sit asperiores hic distinctio quia repellendus.",
      "platform_packages": "linux",
      "awards": {
        "song": false,
        "implementation": false,
        "design": false,
        "best_game": false
      },
      "game_images": ["images"],
      "images_gallery": ["images"],
      "sound_gallery": ["songs"]
    },
    {
      "id": 21,
      "name": "Future Solutions Consultant",
      "semester": "1",
      "year": 2000,
      "cover_image": "http://lorempixel.com/640/480",
      "description": "A magnam deserunt. Quia quia officiis ea voluptas velit vel et. Nobis quia et facere debitis. Adipisci non tempore possimus ut. Dolore iusto nulla ut corrupti veniam a incidunt omnis. Laboriosam provident cum soluta.",
      "platform_packages": "linux",
      "awards": {
        "song": false,
        "implementation": false,
        "design": false,
        "best_game": false
      },
      "game_images": ["images"],
      "images_gallery": ["images"],
      "sound_gallery": ["songs"]
    },
    {
      "id": 22,
      "name": "Central Marketing Designer",
      "semester": "1",
      "year": 2000,
      "cover_image": "http://lorempixel.com/640/480",
      "description": "Nihil et ut similique voluptas similique sunt est. Ipsa consectetur non omnis accusantium fuga in et. Occaecati deserunt corrupti.",
      "platform_packages": "linux",
      "awards": {
        "song": false,
        "implementation": false,
        "design": false,
        "best_game": false
      },
      "game_images": ["images"],
      "images_gallery": ["images"],
      "sound_gallery": ["songs"]
    },
    {
      "id": 23,
      "name": "Direct Web Specialist",
      "semester": "1",
      "year": 2000,
      "cover_image": "http://lorempixel.com/640/480",
      "description": "Beatae perspiciatis dolorem aut dignissimos enim. Repellat omnis itaque accusantium. Nulla quia doloremque fugit. At doloribus earum ad iure.",
      "platform_packages": "linux",
      "awards": {
        "song": false,
        "implementation": false,
        "design": false,
        "best_game": false
      },
      "game_images": ["images"],
      "images_gallery": ["images"],
      "sound_gallery": ["songs"]
    },
    {
      "id": 24,
      "name": "Corporate Optimization Administrator",
      "semester": "1",
      "year": 2000,
      "cover_image": "http://lorempixel.com/640/480",
      "description": "Nesciunt numquam consequatur recusandae cumque vel quia omnis quos impedit. Inventore culpa odio cum. Sunt fuga explicabo ipsum et et consectetur. Fugit et deserunt occaecati. Consequuntur ut sunt aut.",
      "platform_packages": "linux",
      "awards": {
        "song": false,
        "implementation": false,
        "design": false,
        "best_game": false
      },
      "game_images": ["images"],
      "images_gallery": ["images"],
      "sound_gallery": ["songs"]
    },
    {
      "id": 25,
      "name": "National Functionality Producer",
      "semester": "1",
      "year": 2000,
      "cover_image": "http://lorempixel.com/640/480",
      "description": "Quis est molestiae. Facilis dolorem excepturi dicta a repellat autem velit eos odit. Aperiam hic eius velit nemo quae eos.",
      "platform_packages": "linux",
      "awards": {
        "song": false,
        "implementation": false,
        "design": false,
        "best_game": false
      },
      "game_images": ["images"],
      "images_gallery": ["images"],
      "sound_gallery": ["songs"]
    },
    {
      "id": 26,
      "name": "Lead Usability Executive",
      "semester": "1",
      "year": 2000,
      "cover_image": "http://lorempixel.com/640/480",
      "description": "Quasi ullam deleniti. Et aut sit. Cupiditate omnis ut quo amet placeat.",
      "platform_packages": "linux",
      "awards": {
        "song": false,
        "implementation": false,
        "design": false,
        "best_game": false
      },
      "game_images": ["images"],
      "images_gallery": ["images"],
      "sound_gallery": ["songs"]
    },
    {
      "id": 27,
      "name": "Legacy Tactics Engineer",
      "semester": "1",
      "year": 2000,
      "cover_image": "http://lorempixel.com/640/480",
      "description": "Cumque harum autem dolore et corrupti est sint. Est est quia et sapiente dignissimos. Doloremque vero laborum blanditiis velit cupiditate quia aut. Molestiae voluptatem voluptatibus fuga omnis. Quaerat modi itaque quasi nesciunt consequatur quam.",
      "platform_packages": "linux",
      "awards": {
        "song": false,
        "implementation": false,
        "design": false,
        "best_game": false
      },
      "game_images": ["images"],
      "images_gallery": ["images"],
      "sound_gallery": ["songs"]
    },
    {
      "id": 28,
      "name": "Global Configuration Producer",
      "semester": "1",
      "year": 2000,
      "cover_image": "http://lorempixel.com/640/480",
      "description": "Enim pariatur deleniti voluptas non inventore recusandae molestias rerum. Quas id unde. Est deleniti ut cumque omnis cum architecto ipsum. Hic alias excepturi.",
      "platform_packages": "linux",
      "awards": {
        "song": false,
        "implementation": false,
        "design": false,
        "best_game": false
      },
      "game_images": ["images"],
      "images_gallery": ["images"],
      "sound_gallery": ["songs"]
    },
    {
      "id": 29,
      "name": "Senior Configuration Orchestrator",
      "semester": "1",
      "year": 2000,
      "cover_image": "http://lorempixel.com/640/480",
      "description": "Vel rerum non fugit dolorem soluta ipsum ut ullam. Magni ad quaerat corrupti facere commodi minus quam unde. Totam et ipsa unde atque molestias omnis nihil. Veniam praesentium nobis commodi dolorem tempore voluptatem ipsam odio.",
      "platform_packages": "linux",
      "awards": {
        "song": false,
        "implementation": false,
        "design": false,
        "best_game": false
      },
      "game_images": ["images"],
      "images_gallery": ["images"],
      "sound_gallery": ["songs"]
    },
    {
      "id": 30,
      "name": "Internal Optimization Administrator",
      "semester": "1",
      "year": 2000,
      "cover_image": "http://lorempixel.com/640/480",
      "description": "Omnis reprehenderit veniam. Molestiae fugiat est delectus in sit reprehenderit iusto. Officia quod nam blanditiis et possimus corporis est error.",
      "platform_packages": "linux",
      "awards": {
        "song": false,
        "implementation": false,
        "design": false,
        "best_game": false
      },
      "game_images": ["images"],
      "images_gallery": ["images"],
      "sound_gallery": ["songs"]
    },
    {
      "id": 31,
      "name": "Central Configuration Facilitator",
      "semester": "1",
      "year": 2000,
      "cover_image": "http://lorempixel.com/640/480",
      "description": "Perspiciatis dolorem quidem nihil ut repellendus consequatur quam doloremque qui. Soluta fugit officiis nihil autem ea. Rerum quis fugiat maxime dolores.",
      "platform_packages": "linux",
      "awards": {
        "song": false,
        "implementation": false,
        "design": false,
        "best_game": false
      },
      "game_images": ["images"],
      "images_gallery": ["images"],
      "sound_gallery": ["songs"]
    },
    {
      "id": 32,
      "name": "Lead Web Technician",
      "semester": "1",
      "year": 2000,
      "cover_image": "http://lorempixel.com/640/480",
      "description": "Eum tempora dolor laboriosam dignissimos optio. Quos voluptatem nemo ut unde enim molestiae excepturi porro. Facere voluptatem veritatis officiis nostrum possimus molestiae. Asperiores dolor modi eum est fugiat deleniti nam quae dicta.",
      "platform_packages": "linux",
      "awards": {
        "song": false,
        "implementation": false,
        "design": false,
        "best_game": false
      },
      "game_images": ["images"],
      "images_gallery": ["images"],
      "sound_gallery": ["songs"]
    },
    {
      "id": 33,
      "name": "Internal Optimization Liaison",
      "semester": "1",
      "year": 2000,
      "cover_image": "http://lorempixel.com/640/480",
      "description": "Repellat qui culpa. Ut est consequatur ducimus harum ipsa excepturi. Cupiditate similique ea. Pariatur ratione quae porro.",
      "platform_packages": "linux",
      "awards": {
        "song": false,
        "implementation": false,
        "design": false,
        "best_game": false
      },
      "game_images": ["images"],
      "images_gallery": ["images"],
      "sound_gallery": ["songs"]
    },
    {
      "id": 34,
      "name": "Chief Tactics Producer",
      "semester": "1",
      "year": 2000,
      "cover_image": "http://lorempixel.com/640/480",
      "description": "Sunt illum odit non est. Quibusdam dolorum itaque reprehenderit expedita explicabo magni qui. Sed eveniet ipsam praesentium sint. Debitis aut eos modi vel possimus dolorum enim.",
      "platform_packages": "linux",
      "awards": {
        "song": false,
        "implementation": false,
        "design": false,
        "best_game": false
      },
      "game_images": ["images"],
      "images_gallery": ["images"],
      "sound_gallery": ["songs"]
    },
    {
      "id": 35,
      "name": "Human Implementation Director",
      "semester": "1",
      "year": 2000,
      "cover_image": "http://lorempixel.com/640/480",
      "description": "Et et qui sit sed pariatur veniam unde doloremque. Asperiores et voluptatem odit magni dolor esse quidem aut. Nulla nesciunt impedit labore sapiente quis adipisci numquam.",
      "platform_packages": "linux",
      "awards": {
        "song": false,
        "implementation": false,
        "design": false,
        "best_game": false
      },
      "game_images": ["images"],
      "images_gallery": ["images"],
      "sound_gallery": ["songs"]
    },
    {
      "id": 36,
      "name": "Dynamic Research Executive",
      "semester": "1",
      "year": 2000,
      "cover_image": "http://lorempixel.com/640/480",
      "description": "Eos velit quibusdam ullam hic incidunt dignissimos aut temporibus quam. Dolores magni molestiae. Ipsa enim qui. Magnam voluptatibus dolorem quis voluptatem. Sunt qui molestiae numquam mollitia a ipsa natus.",
      "platform_packages": "linux",
      "awards": {
        "song": false,
        "implementation": false,
        "design": false,
        "best_game": false
      },
      "game_images": ["images"],
      "images_gallery": ["images"],
      "sound_gallery": ["songs"]
    },
    {
      "id": 37,
      "name": "Dynamic Optimization Producer",
      "semester": "1",
      "year": 2000,
      "cover_image": "http://lorempixel.com/640/480",
      "description": "Ut consequatur officia culpa quia deserunt dolorem provident possimus. Et dolorum sequi. Illum ad eaque. Officia eaque ipsam. Voluptatem dolores aut aut quia hic perspiciatis. Mollitia autem libero.",
      "platform_packages": "linux",
      "awards": {
        "song": false,
        "implementation": false,
        "design": false,
        "best_game": false
      },
      "game_images": ["images"],
      "images_gallery": ["images"],
      "sound_gallery": ["songs"]
    },
    {
      "id": 38,
      "name": "Product Accounts Consultant",
      "semester": "1",
      "year": 2000,
      "cover_image": "http://lorempixel.com/640/480",
      "description": "Esse non qui nam eligendi nemo ut dolorem aut molestiae. Nostrum dolor libero non. Quia tempore harum iste pariatur. Voluptatem optio et unde dolores non dicta fugiat qui impedit.",
      "platform_packages": "linux",
      "awards": {
        "song": false,
        "implementation": false,
        "design": false,
        "best_game": false
      },
      "game_images": ["images"],
      "images_gallery": ["images"],
      "sound_gallery": ["songs"]
    },
    {
      "id": 39,
      "name": "Product Usability Producer",
      "semester": "1",
      "year": 2000,
      "cover_image": "http://lorempixel.com/640/480",
      "description": "Cupiditate ullam sunt id et. Sunt modi est. Ipsum voluptatem fugiat ut sequi nemo quos animi quis nobis.",
      "platform_packages": "linux",
      "awards": {
        "song": false,
        "implementation": false,
        "design": false,
        "best_game": false
      },
      "game_images": ["images"],
      "images_gallery": ["images"],
      "sound_gallery": ["songs"]
    },
    {
      "id": 40,
      "name": "Product Intranet Designer",
      "semester": "1",
      "year": 2000,
      "cover_image": "http://lorempixel.com/640/480",
      "description": "Doloremque ullam quia et tempora. Quia qui quo est ut quia ut qui fuga. Ex sed sequi.",
      "platform_packages": "linux",
      "awards": {
        "song": false,
        "implementation": false,
        "design": false,
        "best_game": false
      },
      "game_images": ["images"],
      "images_gallery": ["images"],
      "sound_gallery": ["songs"]
    },
    {
      "id": 41,
      "name": "Global Markets Officer",
      "semester": "1",
      "year": 2000,
      "cover_image": "http://lorempixel.com/640/480",
      "description": "Est sed ut corporis excepturi vitae inventore dicta. Occaecati adipisci eos totam similique nobis voluptas ipsam. Provident necessitatibus fuga quidem quis ad.",
      "platform_packages": "linux",
      "awards": {
        "song": false,
        "implementation": false,
        "design": false,
        "best_game": false
      },
      "game_images": ["images"],
      "images_gallery": ["images"],
      "sound_gallery": ["songs"]
    },
    {
      "id": 42,
      "name": "Dynamic Configuration Coordinator",
      "semester": "1",
      "year": 2000,
      "cover_image": "http://lorempixel.com/640/480",
      "description": "Nobis nisi quis repudiandae sit voluptates voluptatibus architecto veritatis consequatur. Repellendus dignissimos sequi quod laudantium ratione dolorem. Perspiciatis et iste. Et qui occaecati dolores consequatur neque in omnis voluptas. Omnis dolorem occaecati culpa. Neque tenetur non voluptatibus perspiciatis sapiente sequi maxime.",
      "platform_packages": "linux",
      "awards": {
        "song": false,
        "implementation": false,
        "design": false,
        "best_game": false
      },
      "game_images": ["images"],
      "images_gallery": ["images"],
      "sound_gallery": ["songs"]
    },
    {
      "id": 43,
      "name": "Regional Identity Analyst",
      "semester": "1",
      "year": 2000,
      "cover_image": "http://lorempixel.com/640/480",
      "description": "Harum nihil nihil autem sint inventore molestiae sed. Quidem tenetur corrupti non et soluta odio. Vitae quidem dolorem. Eum pariatur dolorum assumenda aut modi voluptate. Quos fugiat quidem autem illo autem est.",
      "platform_packages": "linux",
      "awards": {
        "song": false,
        "implementation": false,
        "design": false,
        "best_game": false
      },
      "game_images": ["images"],
      "images_gallery": ["images"],
      "sound_gallery": ["songs"]
    },
    {
      "id": 44,
      "name": "Corporate Intranet Strategist",
      "semester": "1",
      "year": 2000,
      "cover_image": "http://lorempixel.com/640/480",
      "description": "Repellendus deserunt qui quos quia aut consectetur unde. Illo sapiente delectus numquam. Quae qui sit aut doloribus sequi vitae. Velit et omnis corporis sed quia in itaque ut. Reprehenderit dolor hic omnis incidunt excepturi ut. Ut cumque architecto ipsa cumque nam.",
      "platform_packages": "linux",
      "awards": {
        "song": false,
        "implementation": false,
        "design": false,
        "best_game": false
      },
      "game_images": ["images"],
      "images_gallery": ["images"],
      "sound_gallery": ["songs"]
    },
    {
      "id": 45,
      "name": "Customer Optimization Consultant",
      "semester": "1",
      "year": 2000,
      "cover_image": "http://lorempixel.com/640/480",
      "description": "Ex deserunt sed culpa nihil possimus quia. Porro ea dolorem consequuntur id nulla. Est est voluptas accusamus similique in. Laborum molestiae suscipit libero aut debitis labore et autem commodi.",
      "platform_packages": "linux",
      "awards": {
        "song": false,
        "implementation": false,
        "design": false,
        "best_game": false
      },
      "game_images": ["images"],
      "images_gallery": ["images"],
      "sound_gallery": ["songs"]
    },
    {
      "id": 46,
      "name": "Regional Implementation Liaison",
      "semester": "1",
      "year": 2000,
      "cover_image": "http://lorempixel.com/640/480",
      "description": "Deserunt sed excepturi error est quisquam cum ut. Iste nobis aut voluptatum est omnis molestiae ut veritatis eum. Qui harum possimus natus. Et consectetur aspernatur consequatur sit exercitationem similique.",
      "platform_packages": "linux",
      "awards": {
        "song": false,
        "implementation": false,
        "design": false,
        "best_game": false
      },
      "game_images": ["images"],
      "images_gallery": ["images"],
      "sound_gallery": ["songs"]
    },
    {
      "id": 47,
      "name": "Senior Mobility Specialist",
      "semester": "1",
      "year": 2000,
      "cover_image": "http://lorempixel.com/640/480",
      "description": "Et et velit corporis quae fugiat fuga ea occaecati. Aut sint qui. Odio aut quis illo illo ipsum dicta nihil dolorem cum.",
      "platform_packages": "linux",
      "awards": {
        "song": false,
        "implementation": false,
        "design": false,
        "best_game": false
      },
      "game_images": ["images"],
      "images_gallery": ["images"],
      "sound_gallery": ["songs"]
    },
    {
      "id": 48,
      "name": "Senior Implementation Engineer",
      "semester": "1",
      "year": 2000,
      "cover_image": "http://lorempixel.com/640/480",
      "description": "Dicta fugit velit quia consequatur quia vel molestiae consequatur. Sit quam fugiat repellat esse facere ea. Repellendus quisquam ea repellat soluta. Sed et est. Est illum nulla et omnis sed qui laboriosam et sequi.",
      "platform_packages": "linux",
      "awards": {
        "song": false,
        "implementation": false,
        "design": false,
        "best_game": false
      },
      "game_images": ["images"],
      "images_gallery": ["images"],
      "sound_gallery": ["songs"]
    },
    {
      "id": 49,
      "name": "Senior Integration Analyst",
      "semester": "1",
      "year": 2000,
      "cover_image": "http://lorempixel.com/640/480",
      "description": "Asperiores dolorem et fugiat fugit quidem voluptate. Quae ullam quaerat laborum nihil dolores expedita neque. Ut et et sit ducimus molestias et perferendis similique odio. Natus nemo accusantium vitae similique maxime ipsa.",
      "platform_packages": "linux",
      "awards": {
        "song": false,
        "implementation": false,
        "design": false,
        "best_game": false
      },
      "game_images": ["images"],
      "images_gallery": ["images"],
      "sound_gallery": ["songs"]
    }
  ]
}
